{
  "jf": {
    "typo": {
      "caption": {
        "value": {
          "fontFamily": "{jf.font-family.body}",
          "fontSize": "{jf.font-size.body.xs}",
          "lineHeight": "{jf.line-height.short}",
          "letterSpacing": "{jf.letter-spacing.moderate}",
          "fontWeight": "{jf.font-weight.medium}"
        },
        "type": "typography"
      },
      "category-label": {
        "value": {
          "fontFamily": "{jf.font-family.body}",
          "fontWeight": "{jf.font-weight.medium}",
          "fontSize": "{jf.font-size.body.2xs}",
          "lineHeight": "{jf.line-height.short}",
          "letterSpacing": "{jf.letter-spacing.wide}",
          "textCase": "uppercase"
        },
        "type": "typography"
      },
      "display1": {
        "value": {
          "fontFamily": "{jf.font-family.heading}",
          "fontWeight": "{jf.font-weight.bold}",
          "fontSize": "{jf.font-size.display1}",
          "lineHeight": "{jf.line-height.short}",
          "letterSpacing": "{jf.letter-spacing.moderate}",
          "paragraphSpacing": "{jf.dimension.4x}"
        },
        "type": "typography"
      },
      "display2": {
        "value": {
          "fontFamily": "{jf.font-family.heading}",
          "fontWeight": "{jf.font-weight.bold}",
          "fontSize": "{jf.font-size.display2}",
          "lineHeight": "{jf.line-height.short}",
          "letterSpacing": "{jf.letter-spacing.moderate}",
          "paragraphSpacing": "{jf.dimension.4x}"
        },
        "type": "typography"
      },
      "display3": {
        "value": {
          "fontFamily": "{jf.font-family.heading}",
          "fontWeight": "{jf.font-weight.bold}",
          "fontSize": "{jf.font-size.display2}",
          "lineHeight": "{jf.line-height.short}",
          "letterSpacing": "{jf.letter-spacing.moderate}",
          "paragraphSpacing": "{jf.dimension.4x}"
        },
        "type": "typography"
      },
      "h1": {
        "value": {
          "fontFamily": "{jf.font-family.heading}",
          "fontWeight": "{jf.font-weight.bold}",
          "fontSize": "{jf.font-size.h1}",
          "lineHeight": "{jf.line-height.short}",
          "letterSpacing": "{jf.letter-spacing.moderate}",
          "paragraphSpacing": "{jf.dimension.4x}"
        },
        "type": "typography"
      },
      "h2": {
        "value": {
          "fontFamily": "{jf.font-family.heading}",
          "fontWeight": "{jf.font-weight.bold}",
          "fontSize": "{jf.font-size.h2}",
          "lineHeight": "{jf.line-height.short}",
          "letterSpacing": "{jf.letter-spacing.moderate}",
          "paragraphSpacing": "{jf.dimension.4x}"
        },
        "type": "typography"
      },
      "h3": {
        "value": {
          "fontFamily": "{jf.font-family.heading}",
          "fontWeight": "{jf.font-weight.bold}",
          "fontSize": "{jf.font-size.h3}",
          "lineHeight": "{jf.line-height.short}",
          "letterSpacing": "{jf.letter-spacing.moderate}",
          "paragraphSpacing": "{jf.dimension.4x}"
        },
        "type": "typography"
      },
      "h4": {
        "value": {
          "fontFamily": "{jf.font-family.heading}",
          "fontWeight": "{jf.font-weight.medium}",
          "fontSize": "{jf.font-size.h4}",
          "lineHeight": "{jf.line-height.short}",
          "letterSpacing": "{jf.letter-spacing.moderate}",
          "paragraphSpacing": "{jf.dimension.3x}"
        },
        "type": "typography"
      },
      "h5": {
        "value": {
          "fontFamily": "{jf.font-family.heading}",
          "fontWeight": "{jf.font-weight.medium}",
          "fontSize": "{jf.font-size.h5}",
          "lineHeight": "{jf.line-height.moderate}",
          "letterSpacing": "{jf.letter-spacing.moderate}",
          "paragraphSpacing": "{jf.dimension.3x}"
        },
        "type": "typography"
      },
      "h6": {
        "value": {
          "fontFamily": "{jf.font-family.heading}",
          "fontWeight": "{jf.font-weight.medium}",
          "fontSize": "{jf.font-size.h6}",
          "lineHeight": "{jf.line-height.moderate}",
          "letterSpacing": "{jf.letter-spacing.moderate}",
          "paragraphSpacing": "{jf.dimension.3x}"
        },
        "type": "typography"
      },
      "description": {
        "sm": {
          "value": {
            "fontFamily": "{jf.font-family.body}",
            "fontSize": "{jf.font-size.body.sm}",
            "lineHeight": "{jf.line-height.tall}",
            "letterSpacing": "{jf.letter-spacing.moderate}"
          },
          "type": "typography"
        },
        "md": {
          "value": {
            "fontFamily": "{jf.font-family.body}",
            "fontSize": "{jf.font-size.body.md}",
            "lineHeight": "{jf.line-height.tall}",
            "letterSpacing": "{jf.letter-spacing.moderate}"
          },
          "type": "typography"
        },
        "lg": {
          "value": {
            "fontFamily": "{jf.font-family.body}",
            "fontSize": "{jf.font-size.body.lg}",
            "lineHeight": "{jf.line-height.tall}",
            "letterSpacing": "{jf.letter-spacing.moderate}"
          },
          "type": "typography"
        }
      },
      "article": {
        "paragraph": {
          "value": {
            "fontFamily": "{jf.font-family.body}",
            "fontSize": "{jf.font-size.body.lg}",
            "lineHeight": "{jf.line-height.tall}",
            "letterSpacing": "{jf.letter-spacing.moderate}",
            "paragraphSpacing": "{jf.dimension.4x}",
            "paragraphIndent": "{jf.dimension.3_5x}"
          },
          "type": "typography"
        }
      },
      "label": {
        "xs": {
          "value": {
            "fontFamily": "{jf.font-family.body}",
            "fontSize": "{jf.font-size.body.xs}",
            "lineHeight": "{jf.line-height.tall}",
            "letterSpacing": "{jf.letter-spacing.moderate}",
            "fontWeight": "{jf.font-weight.medium}"
          },
          "type": "typography"
        },
        "sm": {
          "value": {
            "fontFamily": "{jf.font-family.body}",
            "fontSize": "{jf.font-size.body.sm}",
            "lineHeight": "{jf.line-height.tall}",
            "letterSpacing": "{jf.letter-spacing.moderate}",
            "fontWeight": "{jf.font-weight.medium}"
          },
          "type": "typography"
        },
        "md": {
          "value": {
            "fontFamily": "{jf.font-family.body}",
            "fontSize": "{jf.font-size.body.md}",
            "lineHeight": "{jf.line-height.tall}",
            "letterSpacing": "{jf.letter-spacing.moderate}",
            "fontWeight": "{jf.font-weight.medium}"
          },
          "type": "typography"
        },
        "lg": {
          "value": {
            "fontFamily": "{jf.font-family.body}",
            "fontSize": "{jf.font-size.body.lg}",
            "lineHeight": "{jf.line-height.tall}",
            "letterSpacing": "{jf.letter-spacing.moderate}",
            "fontWeight": "{jf.font-weight.medium}"
          },
          "type": "typography"
        }
      },
      "code": {
        "sm": {
          "value": {
            "fontFamily": "{jf.font-family.mono}",
            "fontWeight": "{jf.font-weight.regular}",
            "fontSize": "{jf.font-size.body.sm}",
            "lineHeight": "{jf.line-height.tall}",
            "letterSpacing": "{jf.letter-spacing.moderate}"
          },
          "type": "typography"
        },
        "md": {
          "value": {
            "fontFamily": "{jf.font-family.mono}",
            "fontWeight": "{jf.font-weight.regular}",
            "fontSize": "{jf.font-size.body.md}",
            "lineHeight": "{jf.line-height.tall}",
            "letterSpacing": "{jf.letter-spacing.moderate}"
          },
          "type": "typography"
        },
        "lg": {
          "value": {
            "fontFamily": "{jf.font-family.mono}",
            "fontWeight": "{jf.font-weight.regular}",
            "fontSize": "{jf.font-size.body.md}",
            "lineHeight": "{jf.line-height.tall}",
            "letterSpacing": "{jf.letter-spacing.moderate}"
          },
          "type": "typography"
        }
      }
    }
  }
}